{
  "inflections": {
    "singular": {
      "nom": "pomarańcza",
      "gen": "pomarańczy",
      "dat": "pomarańczy",
      "acc": "pomarańczę",
      "ins": "pomarańczą",
      "loc": "pomarańczy",
      "voc": "pomarańczo"
    },
    "plural": {
      "nom": "pomarańcze",
      "gen": { "isTerminus": true, "normal": ["pomarańczy", "pomarańcz"] },
      "dat": "pomarańczom",
      "acc": "pomarańcze",
      "ins": "pomarańczami",
      "loc": "pomarańczach",
      "voc": "pomarańcze"
    }
  }
}
