{
  "inflections": {
    "infinitive": "zacząć",
    "verbalNoun": "zaczęcie",
    "activeAdjectival": false,
    "passiveAdjectival": "zaczęty",
    "contemporaryAdverbial": false,
    "anteriorAdverbial": "zacząwszy",
    "verbal": {
      "conditional": true,
      "future": {
        "impersonal": {
          "singular": {
            "_SingularGenders": "zacznie się"
          },
          "plural": {
            "_PluralGenders": "zacznie się"
          }
        },
        "1per": {
          "singular": {
            "_SingularGendersExcludingNeuter": "zacznę"
          },
          "plural": {
            "_PluralGenders": "zaczniemy"
          }
        },
        "2per": {
          "singular": {
            "_SingularGendersExcludingNeuter": "zaczniesz"
          },
          "plural": {
            "_PluralGenders": "zaczniecie"
          }
        },
        "3per": {
          "singular": {
            "_SingularGenders": "zacznie"
          },
          "plural": {
            "_PluralGenders": "zaczną"
          }
        }
      },
      "imperative": "zacznij",
      "past": {
        "impersonal": {
          "singular": {
            "_SingularGenders": "zaczęto"
          },
          "plural": {
            "_PluralGenders": "zaczęto"
          }
        },
        "1per": {
          "singular": {
            "m": "zacząłem",
            "f": "zaczęłam"
          },
          "plural": {
            "virile": "zaczęliśmy",
            "nonvirile": "zaczęłyśmy"
          }
        },
        "2per": {
          "singular": {
            "m": "zacząłeś",
            "f": "zaczęłaś"
          },
          "plural": {
            "virile": "zaczęliście",
            "nonvirile": "zaczęłyście"
          }
        },
        "3per": {
          "singular": {
            "m": "zaczął",
            "f": "zaczęła",
            "n": "zaczęło"
          },
          "plural": {
            "virile": "zaczęli",
            "nonvirile": "zaczęły"
          }
        }
      },
      "present": false
    }
  }
}
