{
  "inflections": {
    "infinitive": "przebić",
    "verbalNoun": "przebicie",
    "activeAdjectival": false,
    "passiveAdjectival": "przebity",
    "contemporaryAdverbial": false,
    "anteriorAdverbial": "przebiwszy",
    "verbal": {
      "conditional": true,
      "future": {
        "impersonal": {
          "singular": {
            "_SingularGenders": "przebije się"
          },
          "plural": {
            "_PluralGenders": "przebije się"
          }
        },
        "1per": {
          "singular": {
            "_SingularGendersExcludingNeuter": "przebiję"
          },
          "plural": {
            "_PluralGenders": "przebijemy"
          }
        },
        "2per": {
          "singular": {
            "_SingularGendersExcludingNeuter": "przebijesz"
          },
          "plural": {
            "_PluralGenders": "przebijecie"
          }
        },
        "3per": {
          "singular": {
            "_SingularGenders": "przebije"
          },
          "plural": {
            "_PluralGenders": "przebiją"
          }
        }
      },
      "imperative": "przebij",
      "past": {
        "impersonal": {
          "singular": {
            "_SingularGenders": "przebito"
          },
          "plural": {
            "_PluralGenders": "przebito"
          }
        },
        "1per": {
          "singular": {
            "m": "przebiłem",
            "f": "przebiłam"
          },
          "plural": {
            "virile": "przebiliśmy",
            "nonvirile": "przebiłyśmy"
          }
        },
        "2per": {
          "singular": {
            "m": "przebiłeś",
            "f": "przebiłaś"
          },
          "plural": {
            "virile": "przebiliście",
            "nonvirile": "przebiłyście"
          }
        },
        "3per": {
          "singular": {
            "m": "przebił",
            "f": "przebiła",
            "n": "przebiło"
          },
          "plural": {
            "virile": "przebili",
            "nonvirile": "przebiły"
          }
        }
      },
      "present": false
    }
  }
}
