{
  "inflections": {
    "infinitive": "obiecać",
    "verbalNoun": "obiecanie",
    "activeAdjectival": false,
    "passiveAdjectival": "obiecany",
    "contemporaryAdverbial": false,
    "anteriorAdverbial": "obiecawszy",
    "verbal": {
      "conditional": true,
      "future": {
        "impersonal": {
          "singular": {
            "_SingularGenders": "obieca się"
          },
          "plural": {
            "_PluralGenders": "obieca się"
          }
        },
        "1per": {
          "singular": {
            "_SingularGendersExcludingNeuter": "obiecam"
          },
          "plural": {
            "_PluralGenders": "obiecamy"
          }
        },
        "2per": {
          "singular": {
            "_SingularGendersExcludingNeuter": "obiecasz"
          },
          "plural": {
            "_PluralGenders": "obiecacie"
          }
        },
        "3per": {
          "singular": {
            "_SingularGenders": "obieca"
          },
          "plural": {
            "_PluralGenders": "obiecają"
          }
        }
      },
      "imperative": "obiecaj",
      "past": {
        "impersonal": {
          "singular": {
            "_SingularGenders": "obiecano"
          },
          "plural": {
            "_PluralGenders": "obiecano"
          }
        },
        "1per": {
          "singular": {
            "m": "obiecałem",
            "f": "obiecałam"
          },
          "plural": {
            "virile": "obiecaliśmy",
            "nonvirile": "obiecałyśmy"
          }
        },
        "2per": {
          "singular": {
            "m": "obiecałeś",
            "f": "obiecałaś"
          },
          "plural": {
            "virile": "obiecaliście",
            "nonvirile": "obiecałyście"
          }
        },
        "3per": {
          "singular": {
            "m": "obiecał",
            "f": "obiecała",
            "n": "obiecało"
          },
          "plural": {
            "virile": "obiecali",
            "nonvirile": "obiecały"
          }
        }
      },
      "present": false
    }
  }
}
