{
  "inflections": {
    "infinitive": "odsuwać",
    "verbalNoun": "odsuwanie",
    "activeAdjectival": "odsuwający",
    "passiveAdjectival": "odsuwany",
    "contemporaryAdverbial": "odsuwając",
    "anteriorAdverbial": false,
    "verbal": {
      "conditional": true,
      "future": true,
      "imperative": "odsuwaj",
      "past": {
        "impersonal": {
          "singular": {
            "_SingularGenders": "odsuwano"
          },
          "plural": {
            "_PluralGenders": "odsuwano"
          }
        },
        "1per": {
          "singular": {
            "m": "odsuwałem",
            "f": "odsuwałam"
          },
          "plural": {
            "virile": "odsuwaliśmy",
            "nonvirile": "odsuwałyśmy"
          }
        },
        "2per": {
          "singular": {
            "m": "odsuwałeś",
            "f": "odsuwałaś"
          },
          "plural": {
            "virile": "odsuwaliście",
            "nonvirile": "odsuwałyście"
          }
        },
        "3per": {
          "singular": {
            "m": "odsuwał",
            "f": "odsuwała",
            "n": "odsuwało"
          },
          "plural": {
            "virile": "odsuwali",
            "nonvirile": "odsuwały"
          }
        }
      },
      "present": {
        "impersonal": {
          "singular": {
            "_SingularGenders": "odsuwa się"
          },
          "plural": {
            "_PluralGenders": "odsuwa się"
          }
        },
        "1per": {
          "singular": {
            "_SingularGendersExcludingNeuter": "odsuwam"
          },
          "plural": {
            "_PluralGenders": "odsuwamy"
          }
        },
        "2per": {
          "singular": {
            "_SingularGendersExcludingNeuter": "odsuwasz"
          },
          "plural": {
            "_PluralGenders": "odsuwacie"
          }
        },
        "3per": {
          "singular": {
            "_SingularGenders": "odsuwa"
          },
          "plural": {
            "_PluralGenders": "odsuwają"
          }
        }
      }
    }
  }
}
