{
  "inflections": {
    "infinitive": "chwytać",
    "verbalNoun": "chwytanie",
    "activeAdjectival": "chwytający",
    "passiveAdjectival": "chwytany",
    "contemporaryAdverbial": "chwytając",
    "anteriorAdverbial": false,
    "verbal": {
      "conditional": true,
      "future": true,
      "imperative": "chwytaj",
      "past": {
        "impersonal": {
          "singular": {
            "_SingularGenders": "chwytano"
          },
          "plural": {
            "_PluralGenders": "chwytano"
          }
        },
        "1per": {
          "singular": {
            "m": "chwytałem",
            "f": "chwytałam"
          },
          "plural": {
            "virile": "chwytaliśmy",
            "nonvirile": "chwytałyśmy"
          }
        },
        "2per": {
          "singular": {
            "m": "chwytałeś",
            "f": "chwytałaś"
          },
          "plural": {
            "virile": "chwytaliście",
            "nonvirile": "chwytałyście"
          }
        },
        "3per": {
          "singular": {
            "m": "chwytał",
            "f": "chwytała",
            "n": "chwytało"
          },
          "plural": {
            "virile": "chwytali",
            "nonvirile": "chwytały"
          }
        }
      },
      "present": {
        "impersonal": {
          "singular": {
            "_SingularGenders": "chwyta się"
          },
          "plural": {
            "_PluralGenders": "chwyta się"
          }
        },
        "1per": {
          "singular": {
            "_SingularGendersExcludingNeuter": "chwytam"
          },
          "plural": {
            "_PluralGenders": "chwytamy"
          }
        },
        "2per": {
          "singular": {
            "_SingularGendersExcludingNeuter": "chwytasz"
          },
          "plural": {
            "_PluralGenders": "chwytacie"
          }
        },
        "3per": {
          "singular": {
            "_SingularGenders": "chwyta"
          },
          "plural": {
            "_PluralGenders": "chwytają"
          }
        }
      }
    }
  }
}
