{
  "inflections": {
    "infinitive": "obiecywać",
    "verbalNoun": "obiecywanie",
    "activeAdjectival": "obiecujący",
    "passiveAdjectival": "obiecywany",
    "contemporaryAdverbial": "obiecując",
    "anteriorAdverbial": false,
    "verbal": {
      "conditional": true,
      "future": true,
      "imperative": "obiecuj",
      "past": {
        "impersonal": {
          "singular": {
            "_SingularGenders": "obiecywano"
          },
          "plural": {
            "_PluralGenders": "obiecywano"
          }
        },
        "1per": {
          "singular": {
            "m": "obiecywałem",
            "f": "obiecywałam"
          },
          "plural": {
            "virile": "obiecywaliśmy",
            "nonvirile": "obiecywałyśmy"
          }
        },
        "2per": {
          "singular": {
            "m": "obiecywałeś",
            "f": "obiecywałaś"
          },
          "plural": {
            "virile": "obiecywaliście",
            "nonvirile": "obiecywałyście"
          }
        },
        "3per": {
          "singular": {
            "m": "obiecywał",
            "f": "obiecywała",
            "n": "obiecywało"
          },
          "plural": {
            "virile": "obiecywali",
            "nonvirile": "obiecywały"
          }
        }
      },
      "present": {
        "impersonal": {
          "singular": {
            "_SingularGenders": "obiecuje się"
          },
          "plural": {
            "_PluralGenders": "obiecuje się"
          }
        },
        "1per": {
          "singular": {
            "_SingularGendersExcludingNeuter": "obiecuję"
          },
          "plural": {
            "_PluralGenders": "obiecujemy"
          }
        },
        "2per": {
          "singular": {
            "_SingularGendersExcludingNeuter": "obiecujesz"
          },
          "plural": {
            "_PluralGenders": "obiecujecie"
          }
        },
        "3per": {
          "singular": {
            "_SingularGenders": "obiecuje"
          },
          "plural": {
            "_PluralGenders": "obiecują"
          }
        }
      }
    }
  }
}
