{
  "inflections": {
    "infinitive": "opowiedzieć",
    "verbalNoun": "opowiedzenie",
    "activeAdjectival": false,
    "passiveAdjectival": "opowiedziany",
    "contemporaryAdverbial": false,
    "anteriorAdverbial": "opowiedziawszy",
    "verbal": {
      "conditional": true,
      "future": {
        "impersonal": {
          "singular": {
            "_SingularGenders": "opowie się"
          },
          "plural": {
            "_PluralGenders": "opowie się"
          }
        },
        "1per": {
          "singular": {
            "_SingularGendersExcludingNeuter": "opowiem"
          },
          "plural": {
            "_PluralGenders": "opowiemy"
          }
        },
        "2per": {
          "singular": {
            "_SingularGendersExcludingNeuter": "opowiesz"
          },
          "plural": {
            "_PluralGenders": "opowiecie"
          }
        },
        "3per": {
          "singular": {
            "_SingularGenders": "opowie"
          },
          "plural": {
            "_PluralGenders": "opowiedzą"
          }
        }
      },
      "imperative": "opowiedz",
      "past": {
        "impersonal": {
          "singular": {
            "_SingularGenders": "opowiedziano"
          },
          "plural": {
            "_PluralGenders": "opowiedziano"
          }
        },
        "1per": {
          "singular": {
            "m": "opowiedziałem",
            "f": "opowiedziałam"
          },
          "plural": {
            "virile": "opowiedzieliśmy",
            "nonvirile": "opowiedziałyśmy"
          }
        },
        "2per": {
          "singular": {
            "m": "opowiedziałeś",
            "f": "opowiedziałaś"
          },
          "plural": {
            "virile": "opowiedzieliście",
            "nonvirile": "opowiedziałyście"
          }
        },
        "3per": {
          "singular": {
            "m": "opowiedział",
            "f": "opowiedziała",
            "n": "opowiedziało"
          },
          "plural": {
            "virile": "opowiedzieli",
            "nonvirile": "opowiedziały"
          }
        }
      },
      "present": false
    }
  }
}
