{
  "inflections": {
    "infinitive": "ukształtować",
    "verbalNoun": "ukształtowanie",
    "activeAdjectival": false,
    "passiveAdjectival": "ukształtowany",
    "contemporaryAdverbial": false,
    "anteriorAdverbial": "ukształtowawszy",
    "verbal": {
      "conditional": true,
      "future": {
        "impersonal": {
          "singular": {
            "_SingularGenders": "ukształtuje się"
          },
          "plural": {
            "_PluralGenders": "ukształtuje się"
          }
        },
        "1per": {
          "singular": {
            "_SingularGendersExcludingNeuter": "ukształtuję"
          },
          "plural": {
            "_PluralGenders": "ukształtujemy"
          }
        },
        "2per": {
          "singular": {
            "_SingularGendersExcludingNeuter": "ukształtujesz"
          },
          "plural": {
            "_PluralGenders": "ukształtujecie"
          }
        },
        "3per": {
          "singular": {
            "_SingularGenders": "ukształtuje"
          },
          "plural": {
            "_PluralGenders": "ukształtują"
          }
        }
      },
      "imperative": "ukształtuj",
      "past": {
        "impersonal": {
          "singular": {
            "_SingularGenders": "ukształtowano"
          },
          "plural": {
            "_PluralGenders": "ukształtowano"
          }
        },
        "1per": {
          "singular": {
            "m": "ukształtowałem",
            "f": "ukształtowałam"
          },
          "plural": {
            "virile": "ukształtowaliśmy",
            "nonvirile": "ukształtowałyśmy"
          }
        },
        "2per": {
          "singular": {
            "m": "ukształtowałeś",
            "f": "ukształtowałaś"
          },
          "plural": {
            "virile": "ukształtowaliście",
            "nonvirile": "ukształtowałyście"
          }
        },
        "3per": {
          "singular": {
            "m": "ukształtował",
            "f": "ukształtowała",
            "n": "ukształtowało"
          },
          "plural": {
            "virile": "ukształtowali",
            "nonvirile": "ukształtowały"
          }
        }
      },
      "present": false
    }
  }
}
