{
  "inflections": {
    "infinitive": "dawać",
    "verbalNoun": "dawanie",
    "activeAdjectival": "dający",
    "passiveAdjectival": "dawany",
    "contemporaryAdverbial": "dając",
    "anteriorAdverbial": false,
    "verbal": {
      "conditional": true,
      "future": true,
      "imperative": "dawaj",
      "past": {
        "impersonal": {
          "singular": {
            "_SingularGenders": "dawano"
          },
          "plural": {
            "_PluralGenders": "dawano"
          }
        },
        "1per": {
          "singular": {
            "m": "dawałem",
            "f": "dawałam"
          },
          "plural": {
            "virile": "dawaliśmy",
            "nonvirile": "dawałyśmy"
          }
        },
        "2per": {
          "singular": {
            "m": "dawałeś",
            "f": "dawałaś"
          },
          "plural": {
            "virile": "dawaliście",
            "nonvirile": "dawałyście"
          }
        },
        "3per": {
          "singular": {
            "m": "dawał",
            "f": "dawała",
            "n": "dawało"
          },
          "plural": {
            "virile": "dawali",
            "nonvirile": "dawały"
          }
        }
      },
      "present": {
        "impersonal": {
          "singular": {
            "_SingularGenders": "daje się"
          },
          "plural": {
            "_PluralGenders": "daje się"
          }
        },
        "1per": {
          "singular": {
            "_SingularGendersExcludingNeuter": "daję"
          },
          "plural": {
            "_PluralGenders": "dajemy"
          }
        },
        "2per": {
          "singular": {
            "_SingularGendersExcludingNeuter": "dajesz"
          },
          "plural": {
            "_PluralGenders": "dajecie"
          }
        },
        "3per": {
          "singular": {
            "_SingularGenders": "daje"
          },
          "plural": {
            "_PluralGenders": "dają"
          }
        }
      }
    }
  }
}
